<?xml version="1.0" encoding="UTF-8"?>
<!DOCTYPE mapper PUBLIC "-//mybatis.org//DTD Mapper 3.0//EN" "http://mybatis.org/dtd/mybatis-3-mapper.dtd">
<mapper namespace="com.ksource.liangfa.mapper.FormDefMapper">
  <resultMap id="BaseResultMap" type="com.ksource.liangfa.domain.FormDef">
    <!--
      WARNING - @mbggenerated
      This element is automatically generated by MyBatis Generator, do not modify.
      This element was generated on Mon May 09 18:15:35 CST 2011.
    -->
    <id column="FORM_DEF_ID" jdbcType="DECIMAL" property="formDefId" />
    <result column="FORM_DEF_NAME" jdbcType="VARCHAR" property="formDefName" />
  </resultMap>
  <resultMap extends="BaseResultMap" id="ResultMapWithBLOBs" type="com.ksource.liangfa.domain.FormDef">
    <!--
      WARNING - @mbggenerated
      This element is automatically generated by MyBatis Generator, do not modify.
      This element was generated on Mon May 09 18:15:35 CST 2011.
    -->
    <result column="JSON_VIEW" jdbcType="CLOB" property="jsonView" />
  </resultMap>
  <sql id="Example_Where_Clause">
    <!--
      WARNING - @mbggenerated
      This element is automatically generated by MyBatis Generator, do not modify.
      This element was generated on Mon May 09 18:15:35 CST 2011.
    -->
    <where>
      <foreach collection="oredCriteria" item="criteria" separator="or">
        <if test="criteria.valid">
          <trim prefix="(" prefixOverrides="and" suffix=")">
            <foreach collection="criteria.criteria" item="criterion">
              <choose>
                <when test="criterion.noValue">
                  and ${criterion.condition}
                </when>
                <when test="criterion.singleValue">
                  and ${criterion.condition} #{criterion.value}
                </when>
                <when test="criterion.betweenValue">
                  and ${criterion.condition} #{criterion.value} and #{criterion.secondValue}
                </when>
                <when test="criterion.listValue">
                  and ${criterion.condition}
                  <foreach close=")" collection="criterion.value" item="listItem" open="(" separator=",">
                    #{listItem}
                  </foreach>
                </when>
              </choose>
            </foreach>
          </trim>
        </if>
      </foreach>
    </where>
  </sql>
  <sql id="Update_By_Example_Where_Clause">
    <!--
      WARNING - @mbggenerated
      This element is automatically generated by MyBatis Generator, do not modify.
      This element was generated on Mon May 09 18:15:35 CST 2011.
    -->
    <where>
      <foreach collection="example.oredCriteria" item="criteria" separator="or">
        <if test="criteria.valid">
          <trim prefix="(" prefixOverrides="and" suffix=")">
            <foreach collection="criteria.criteria" item="criterion">
              <choose>
                <when test="criterion.noValue">
                  and ${criterion.condition}
                </when>
                <when test="criterion.singleValue">
                  and ${criterion.condition} #{criterion.value}
                </when>
                <when test="criterion.betweenValue">
                  and ${criterion.condition} #{criterion.value} and #{criterion.secondValue}
                </when>
                <when test="criterion.listValue">
                  and ${criterion.condition}
                  <foreach close=")" collection="criterion.value" item="listItem" open="(" separator=",">
                    #{listItem}
                  </foreach>
                </when>
              </choose>
            </foreach>
          </trim>
        </if>
      </foreach>
    </where>
  </sql>
  <sql id="Base_Column_List">
    <!--
      WARNING - @mbggenerated
      This element is automatically generated by MyBatis Generator, do not modify.
      This element was generated on Mon May 09 18:15:35 CST 2011.
    -->
    FORM_DEF_ID, FORM_DEF_NAME
  </sql>
  <sql id="Blob_Column_List">
    <!--
      WARNING - @mbggenerated
      This element is automatically generated by MyBatis Generator, do not modify.
      This element was generated on Mon May 09 18:15:35 CST 2011.
    -->
    JSON_VIEW
  </sql>
  <select id="selectByExampleWithBLOBs" parameterType="com.ksource.liangfa.domain.FormDefExample" resultMap="ResultMapWithBLOBs">
    <!--
      WARNING - @mbggenerated
      This element is automatically generated by MyBatis Generator, do not modify.
      This element was generated on Mon May 09 18:15:35 CST 2011.
    -->
    select
    <if test="distinct">
      distinct
    </if>
    <include refid="Base_Column_List" />
    ,
    <include refid="Blob_Column_List" />
    from FORM_DEF
    <if test="_parameter != null">
      <include refid="Example_Where_Clause" />
    </if>
    <if test="orderByClause != null">
      order by ${orderByClause}
    </if>
  </select>
  <select id="selectByExample" parameterType="com.ksource.liangfa.domain.FormDefExample" resultMap="BaseResultMap">
    <!--
      WARNING - @mbggenerated
      This element is automatically generated by MyBatis Generator, do not modify.
      This element was generated on Mon May 09 18:15:35 CST 2011.
    -->
    select
    <if test="distinct">
      distinct
    </if>
    <include refid="Base_Column_List" />
    from FORM_DEF
    <if test="_parameter != null">
      <include refid="Example_Where_Clause" />
    </if>
    <if test="orderByClause != null">
      order by ${orderByClause}
    </if>
  </select>
  <select id="selectByPrimaryKey" parameterType="Integer" resultMap="ResultMapWithBLOBs">
    <!--
      WARNING - @mbggenerated
      This element is automatically generated by MyBatis Generator, do not modify.
      This element was generated on Mon May 09 18:15:35 CST 2011.
    -->
    select 
    <include refid="Base_Column_List" />
    ,
    <include refid="Blob_Column_List" />
    from FORM_DEF
    where FORM_DEF_ID = #{formDefId,jdbcType=DECIMAL}
  </select>
  <delete id="deleteByPrimaryKey" parameterType="Integer">
    <!--
      WARNING - @mbggenerated
      This element is automatically generated by MyBatis Generator, do not modify.
      This element was generated on Mon May 09 18:15:35 CST 2011.
    -->
    delete from FORM_DEF
    where FORM_DEF_ID = #{formDefId,jdbcType=DECIMAL}
  </delete>
  <delete id="deleteByExample" parameterType="com.ksource.liangfa.domain.FormDefExample">
    <!--
      WARNING - @mbggenerated
      This element is automatically generated by MyBatis Generator, do not modify.
      This element was generated on Mon May 09 18:15:35 CST 2011.
    -->
    delete from FORM_DEF
    <if test="_parameter != null">
      <include refid="Example_Where_Clause" />
    </if>
  </delete>
  <insert id="insert" parameterType="com.ksource.liangfa.domain.FormDef">
    <!--
      WARNING - @mbggenerated
      This element is automatically generated by MyBatis Generator, do not modify.
      This element was generated on Mon May 09 18:15:35 CST 2011.
    -->
    insert into FORM_DEF (FORM_DEF_ID, FORM_DEF_NAME, JSON_VIEW
      )
    values (#{formDefId,jdbcType=DECIMAL}, #{formDefName,jdbcType=VARCHAR}, #{jsonView,jdbcType=CLOB}
      )
  </insert>
  <insert id="insertSelective" parameterType="com.ksource.liangfa.domain.FormDef">
    <!--
      WARNING - @mbggenerated
      This element is automatically generated by MyBatis Generator, do not modify.
      This element was generated on Mon May 09 18:15:35 CST 2011.
    -->
    insert into FORM_DEF
    <trim prefix="(" suffix=")" suffixOverrides=",">
      <if test="formDefId != null">
        FORM_DEF_ID,
      </if>
      <if test="formDefName != null">
        FORM_DEF_NAME,
      </if>
      <if test="jsonView != null">
        JSON_VIEW,
      </if>
    </trim>
    <trim prefix="values (" suffix=")" suffixOverrides=",">
      <if test="formDefId != null">
        #{formDefId,jdbcType=DECIMAL},
      </if>
      <if test="formDefName != null">
        #{formDefName,jdbcType=VARCHAR},
      </if>
      <if test="jsonView != null">
        #{jsonView,jdbcType=CLOB},
      </if>
    </trim>
  </insert>
  <select id="countByExample" parameterType="com.ksource.liangfa.domain.FormDefExample" resultType="java.lang.Integer">
    <!--
      WARNING - @mbggenerated
      This element is automatically generated by MyBatis Generator, do not modify.
      This element was generated on Mon May 09 18:15:35 CST 2011.
    -->
    select count(*) from FORM_DEF
    <if test="_parameter != null">
      <include refid="Example_Where_Clause" />
    </if>
  </select>
  <update id="updateByExampleSelective" parameterType="map">
    <!--
      WARNING - @mbggenerated
      This element is automatically generated by MyBatis Generator, do not modify.
      This element was generated on Mon May 09 18:15:35 CST 2011.
    -->
    update FORM_DEF
    <set>
      <if test="record.formDefId != null">
        FORM_DEF_ID = #{record.formDefId,jdbcType=DECIMAL},
      </if>
      <if test="record.formDefName != null">
        FORM_DEF_NAME = #{record.formDefName,jdbcType=VARCHAR},
      </if>
      <if test="record.jsonView != null">
        JSON_VIEW = #{record.jsonView,jdbcType=CLOB},
      </if>
    </set>
    <if test="_parameter != null">
      <include refid="Update_By_Example_Where_Clause" />
    </if>
  </update>
  <update id="updateByExampleWithBLOBs" parameterType="map">
    <!--
      WARNING - @mbggenerated
      This element is automatically generated by MyBatis Generator, do not modify.
      This element was generated on Mon May 09 18:15:35 CST 2011.
    -->
    update FORM_DEF
    set FORM_DEF_ID = #{record.formDefId,jdbcType=DECIMAL},
      FORM_DEF_NAME = #{record.formDefName,jdbcType=VARCHAR},
      JSON_VIEW = #{record.jsonView,jdbcType=CLOB}
    <if test="_parameter != null">
      <include refid="Update_By_Example_Where_Clause" />
    </if>
  </update>
  <update id="updateByExample" parameterType="map">
    <!--
      WARNING - @mbggenerated
      This element is automatically generated by MyBatis Generator, do not modify.
      This element was generated on Mon May 09 18:15:35 CST 2011.
    -->
    update FORM_DEF
    set FORM_DEF_ID = #{record.formDefId,jdbcType=DECIMAL},
      FORM_DEF_NAME = #{record.formDefName,jdbcType=VARCHAR}
    <if test="_parameter != null">
      <include refid="Update_By_Example_Where_Clause" />
    </if>
  </update>
  <update id="updateByPrimaryKeySelective" parameterType="com.ksource.liangfa.domain.FormDef">
    <!--
      WARNING - @mbggenerated
      This element is automatically generated by MyBatis Generator, do not modify.
      This element was generated on Mon May 09 18:15:35 CST 2011.
    -->
    update FORM_DEF
    <set>
      <if test="formDefName != null">
        FORM_DEF_NAME = #{formDefName,jdbcType=VARCHAR},
      </if>
      <if test="jsonView != null">
        JSON_VIEW = #{jsonView,jdbcType=CLOB},
      </if>
    </set>
    where FORM_DEF_ID = #{formDefId,jdbcType=DECIMAL}
  </update>
  <update id="updateByPrimaryKeyWithBLOBs" parameterType="com.ksource.liangfa.domain.FormDef">
    <!--
      WARNING - @mbggenerated
      This element is automatically generated by MyBatis Generator, do not modify.
      This element was generated on Mon May 09 18:15:35 CST 2011.
    -->
    update FORM_DEF
    set FORM_DEF_NAME = #{formDefName,jdbcType=VARCHAR},
      JSON_VIEW = #{jsonView,jdbcType=CLOB}
    where FORM_DEF_ID = #{formDefId,jdbcType=DECIMAL}
  </update>
  <update id="updateByPrimaryKey" parameterType="com.ksource.liangfa.domain.FormDef">
    <!--
      WARNING - @mbggenerated
      This element is automatically generated by MyBatis Generator, do not modify.
      This element was generated on Mon May 09 18:15:35 CST 2011.
    -->
    update FORM_DEF
    set FORM_DEF_NAME = #{formDefName,jdbcType=VARCHAR}
    where FORM_DEF_ID = #{formDefId,jdbcType=DECIMAL}
  </update>
</mapper>